rocinante/__init__.py
rocinante/common.py
Python_Rocinante-0.0.1.dist-info/LICENSE
Python_Rocinante-0.0.1.dist-info/METADATA
Python_Rocinante-0.0.1.dist-info/WHEEL
Python_Rocinante-0.0.1.dist-info/top_level.txt
Python_Rocinante-0.0.1.dist-info/zip-safe
Python_Rocinante-0.0.1.dist-info/RECORD
