Metadata-Version: 2.1
Name: Python-Rocinante
Version: 0.0.1
Summary: Python library for happy in using.
Home-page: http://gitee.com/PyRocinante
Author: Chisheng Chen
Author-email: gndlwccw@163.com
License: MIT-0
License-File: LICENSE
